taupe/__init__.py
taupe/__main__.py
taupe/exit_codes.py
taupe-1.2.0.dist-info/LICENSE
taupe-1.2.0.dist-info/METADATA
taupe-1.2.0.dist-info/WHEEL
taupe-1.2.0.dist-info/entry_points.txt
taupe-1.2.0.dist-info/top_level.txt
taupe-1.2.0.dist-info/RECORD
