Metadata-Version: 2.1
Name: taupe
Version: 1.2.0
Summary: Taupe: a tool to extract URLs from your personal Twitter archive
Home-page: https://github.com/mhucka/taupe
Author: Mike Hucka
Author-email: mhucka@caltech.edu
License: MIT
Project-URL: Source Code, https://github.com/mhucka/taupe
Project-URL: Bug Tracker, https://github.com/mhucka/taupe/issues
Keywords: Python,applications
Platform: UNKNOWN
Classifier: Development Status :: 3 - Alpha
Classifier: Environment :: Console
Classifier: License :: OSI Approved :: MIT License
Classifier: Intended Audience :: Science/Research
Classifier: Operating System :: MacOS :: MacOS X
Classifier: Operating System :: POSIX
Classifier: Operating System :: POSIX :: Linux
Classifier: Operating System :: Unix
Classifier: Programming Language :: Python
Classifier: Programming Language :: Python :: 3.8
Requires-Python: >=3.8
License-File: LICENSE
Requires-Dist: aenum (>=3.1.0)
Requires-Dist: commonpy (==1.9.5)
Requires-Dist: plac (==1.3.5)
Requires-Dist: rich (>=12.6.0)
Requires-Dist: setuptools (==58.3.0)
Requires-Dist: sidetrack (>=2.0.1)
Provides-Extra: dev
Requires-Dist: aenum (>=3.1.0) ; extra == 'dev'
Requires-Dist: commonpy (==1.9.5) ; extra == 'dev'
Requires-Dist: plac (==1.3.5) ; extra == 'dev'
Requires-Dist: rich (>=12.6.0) ; extra == 'dev'
Requires-Dist: setuptools (==58.3.0) ; extra == 'dev'
Requires-Dist: sidetrack (>=2.0.1) ; extra == 'dev'
Requires-Dist: pytest (>=6.2.5) ; extra == 'dev'
Requires-Dist: pytest-cov (>=3.0.0) ; extra == 'dev'
Requires-Dist: pytest-mock (>=3.7.0) ; extra == 'dev'
Requires-Dist: flake8 (>=4.0.1) ; extra == 'dev'
Requires-Dist: flake8-bugbear (>=22.4.25) ; extra == 'dev'
Requires-Dist: flake8-builtins (>=1.5.3) ; extra == 'dev'
Requires-Dist: flake8-comprehensions (>=3.8.0) ; extra == 'dev'
Requires-Dist: flake8-executable (>=2.1.1) ; extra == 'dev'
Requires-Dist: flake8-implicit-str-concat (>=0.3.0) ; extra == 'dev'
Requires-Dist: flake8-pie (>=0.15.0) ; extra == 'dev'
Requires-Dist: flake8-simplify (>=0.19.2) ; extra == 'dev'
Requires-Dist: twine ; extra == 'dev'
